cloud_enforcer/__init__.py
cloud_enforcer/cli.py
cloud_enforcer/cloud_enforcer.py
cloud_enforcer-0.2.4.dist-info/AUTHORS.rst
cloud_enforcer-0.2.4.dist-info/LICENSE
cloud_enforcer-0.2.4.dist-info/METADATA
cloud_enforcer-0.2.4.dist-info/WHEEL
cloud_enforcer-0.2.4.dist-info/entry_points.txt
cloud_enforcer-0.2.4.dist-info/top_level.txt
cloud_enforcer-0.2.4.dist-info/RECORD
