Metadata-Version: 2.1
Name: cloud-enforcer
Version: 0.2.4
Summary: Configuration enforcement dependencies for  secure microcosms in cloud environments
Home-page: https://github.com/dimitry-dukhovny/cloud_enforcer
Author: Dimitry Dukhovny
Author-email: dimitry@dukhovny.net
License: MIT license
Keywords: cloud_enforcer
Platform: UNKNOWN
Classifier: Development Status :: 2 - Pre-Alpha
Classifier: Intended Audience :: Developers
Classifier: License :: OSI Approved :: MIT License
Classifier: Natural Language :: English
Classifier: Programming Language :: Python :: 3
Classifier: Programming Language :: Python :: 3.6
Classifier: Programming Language :: Python :: 3.7
Classifier: Programming Language :: Python :: 3.8
Requires-Python: >=3.6
Requires-Dist: pyaml
Requires-Dist: boto
Requires-Dist: boto3
Requires-Dist: awscli
Requires-Dist: pywinrm
Requires-Dist: pykerberos
Requires-Dist: requests-credssp
Requires-Dist: ansible
Requires-Dist: ansible-runner
Requires-Dist: git-remote-codecommit
Requires-Dist: cryptography
Requires-Dist: cffi (>=1.12)
Requires-Dist: pycparser
Requires-Dist: urllib3 (>=1.26.6)
Requires-Dist: rust
Requires-Dist: colorama
Requires-Dist: click
Requires-Dist: setuptools-rust
Requires-Dist: wheel (>=0.37.0)
